dpaste_magic/__init__.py
dpaste_magic/dpaste_magic.py
dpaste_magic-0.3.0.dist-info/licenses/LICENSE
dpaste_magic-0.3.0.dist-info/METADATA
dpaste_magic-0.3.0.dist-info/WHEEL
dpaste_magic-0.3.0.dist-info/top_level.txt
dpaste_magic-0.3.0.dist-info/RECORD
